{
    "basic_info": {
      "description_header": "Hello",
      "description": "👋 I'm Rexie Esmeralda and I am currently a striving software developer student in hopes of making this my career! ",
      "section_name": {
        "about": "About me",
        "projects": "Projects",
        "skills": "Skills",
        "experience": "Experience"
      }
    },
    "projects": [
      {
        "title": "Web-Arcade",
        "startDate": "2022",
        "description": "The most expanded application I had opportunity to work with. I've learned many technologies and my code was reviewed by awesome curator. Application handles all adoption processess and allows to store all evidence on adopting animals from animal shelter.",
        "images": [
          "images/portfolio/webArcade/webarcade.png",
          "images/portfolio/webArcade/wa2.png"
        ],
        "url": "https://web-arcade-00.github.io/Web-Arcade/",
        "technologies": [
          {
            "class": "devicon-javascript-plain",
            "name": "JavaScript"
          },
          {
            "class": "devicon-html-plain",
            "name": "HTML"
          },
          {
            "class": "devicon-css-plain",
            "name": "CSS"
          }
        ]
      },
      {
        "title": "Photography",
        "startDate": "2018",
        "description": "Personal project for study subject. I was responsible for testing photography application that optimizes images with popular algorithms used by graphic editors like Pixlr or Adobe Photoshop. I've earned A grade :)",
        "images": [
          "images/portfolio/photography/p1.jpg",
          "images/portfolio/photography/p2.jpg"
        ],
        "url": "https://github.com",
        "technologies": [
          {
            "class": "devicon-react-original",
            "name": "React"
          },
          {
            "class": "devicon-javascript-plain",
            "name": "JavaScript"
          }
        ]
      },
      {
        "title": "3D Object Viewer",
        "startDate": "2015",
        "description": "One of the first apps I was working on my internship. I had to develop front-end implementation for app that shows 3D models of known buildings. This was also my first project in Angular framework. I've learned a lot!",
        "images": [
          "images/portfolio/adventure/p1.jpg",
          "images/portfolio/adventure/p2.jpg"
        ],
        "url": "https://github.com",
        "technologies": [
          {
            "class": "devicon-angularjs-plain",
            "name": "Angular"
          },
          {
            "class": "devicon-typescript-plain",
            "name": "TypeScript"
          },
          {
            "class": "devicon-csharp-plain",
            "name": "C#"
          }
        ]
      }
    ],
    "experience": [
      {
        "company": "Code Fellows",
        "title": "Student",
        "years": "05.2022 - Present",
        "mainTech": [
          "Angular 8/9/10"
        ],
        "technologies": [
          "JavaScript",
          "HTML",
          "CSS",
          "React"
        ]
      },
      {
        "company": "US Navy",
        "title": "Lead Hydraulic Technician",
        "years": "02.2016-02.2022",
        "mainTech": [
          
        ],
        "technologies": [

        ]
      }
    ]
  }
